{"episode_list":[{"episode_id":"1","episode_name":"\u559c\u591a\u898b\u67daVi\uff9a\uff6f\uff7d\uff9d\uff74\uff8b\uff9f\uff7f\uff70\uff84\uff9e1","episode_voice":"0"},{"episode_id":"2","episode_name":"\u559c\u591a\u898b\u67daVo\uff9a\uff6f\uff7d\uff9d\uff74\uff8b\uff9f\uff7f\uff70\uff84\uff9e1","episode_voice":"0"},{"episode_id":"3","episode_name":"\u559c\u591a\u898b\u67daDa\uff9a\uff6f\uff7d\uff9d\uff74\uff8b\uff9f\uff7f\uff70\uff84\uff9e1","episode_voice":"0"},{"episode_id":"4","episode_name":"\u559c\u591a\u898b\u67da\uff7d\uff83\uff6f\uff8c\uff9f\uff71\uff6f\uff8c\uff9f\uff74\uff8b\uff9f\uff7f\uff70\uff84\uff9e1","episode_voice":"0"},{"episode_id":"5","episode_name":"\u559c\u591a\u898b\u67daVi\uff9a\uff6f\uff7d\uff9d\uff74\uff8b\uff9f\uff7f\uff70\uff84\uff9e2","episode_voice":"0"},{"episode_id":"6","episode_name":"\u559c\u591a\u898b\u67daVo\uff9a\uff6f\uff7d\uff9d\uff74\uff8b\uff9f\uff7f\uff70\uff84\uff9e2","episode_voice":"0"},{"episode_id":"7","episode_name":"\u559c\u591a\u898b\u67daDa\uff9a\uff6f\uff7d\uff9d\uff74\uff8b\uff9f\uff7f\uff70\uff84\uff9e2","episode_voice":"0"},{"episode_id":"8","episode_name":"\u559c\u591a\u898b\u67da\uff7d\uff83\uff6f\uff8c\uff9f\uff71\uff6f\uff8c\uff9f\uff74\uff8b\uff9f\uff7f\uff70\uff84\uff9e2","episode_voice":"0"}],"idol_message":"\u306d\u3047\u67da\uff8c\uff67\uff6f\uff7c\uff6e\uff9d\uff7c\uff6e\uff70\uff64\u898b\u305f\u3044? \u3058\u3083\u3042\uff64\u3042\u3063\u3061\u304b\u3089\u6b69\u3044\u3066\u304f\u308b\u304b\u3089\uff64\uff8c\uff9f\uff9b\uff83\uff9e\uff6d\uff70\uff7b\uff70\u306fBGM\u3092\u304a\u9858\u3044\u266a","idol_attribute":"3"}